{
  "name": "Mechanical Crafter",
  "icon": "create:mechanical_crafter",
  "category": "consumers",
  "sortnum": 11,
  "pages": [
    {
      "type": "text",
      "text": "Mechanical crafters are Create's solution to automatic crafting.$(br2)They function by holding an item in their single slot; when all Mechanical Crafters in an array have an item, they'll mash them together with the same precision a Player can. Make sure the $(l)arrows$() on the Crafters point towards a $(l)common exit$()."
    },
    {
      "type": "multiblock",
      "name": "Mechanical Crafters",
      "multiblock": {
        "pattern": [
          [" >>> ","     "],
          [" CCC ","  0  "],
          [" CCC ","     "]
        ],
        "mapping": {
          "C": "create:mechanical_crafter[facing=east]",
          ">": "create:mechanical_crafter[facing=east,pointing=right]"
        }
      },
      "enable_visualize": false,
      "text": "Hey look, a crafting bench. But who says it needs to be 3x3? Make whatever shape you need!"
    },
    {
      "type": "spotlight",
      "item": "create:crafter_slot_cover",
      "text": "If you need empty spaces in a crafting array and don't (or can't) just remove those crafters from the array, try using a Slot Cover! Made from a piece of brass plate, these fit snugly on a Mechanical Crafter's slot and won't be moved during assembly."
    },
    {
      "type": "crafting",
      "recipe": "create:crafting/kinetics/mechanical_crafter",
      "recipe2": "create:crafting/kinetics/crafter_slot_cover",
      "text": "Quis fabricat ipsos fabrica?"
    }
  ]
}